angular_django/__init__.py
angular_django/metadata.py
angular_django/pagination.py
angular_django/rest_framework.py
angular_django/typescript.py
angular_django-0.0.1.dist-info/LICENSE
angular_django-0.0.1.dist-info/METADATA
angular_django-0.0.1.dist-info/WHEEL
angular_django-0.0.1.dist-info/top_level.txt
angular_django-0.0.1.dist-info/RECORD
