Metadata-Version: 2.1
Name: angular-django
Version: 0.0.1
Summary: Django Rest Framework API for Angular with self-building classes, forms, and listings
Home-page: https://github.com/Nekmo/angular-django/
Author: Nekmo
Author-email: contacto@nekmo.com
License: MIT
Download-URL: https://github.com/Nekmo/angular-django/archive/master.zip
Keywords: angular-django
Platform: linux
Classifier: License :: OSI Approved :: MIT License
Classifier: Programming Language :: Python :: 3.6
Classifier: Programming Language :: Python :: 3 :: Only
Classifier: Programming Language :: Python :: 3.7
Classifier: Programming Language :: Python :: 3.8
Classifier: Programming Language :: Python :: 3.9
Classifier: Operating System :: POSIX
Classifier: Operating System :: POSIX :: Linux
Classifier: Natural Language :: English
Classifier: Development Status :: 5 - Production/Stable
Requires-Dist: Django
Requires-Dist: djangorestframework
